m4rkw_tracing-0.1.26.dist-info/licenses/LICENSE
tracing/__init__.py
tracing/py.typed
tracing/tracing.py
tracing/update_tracing.py
m4rkw_tracing-0.1.26.dist-info/METADATA
m4rkw_tracing-0.1.26.dist-info/WHEEL
m4rkw_tracing-0.1.26.dist-info/entry_points.txt
m4rkw_tracing-0.1.26.dist-info/top_level.txt
m4rkw_tracing-0.1.26.dist-info/RECORD
