Metadata-Version: 2.4
Name: m4rkw-tracing
Version: 0.1.26
Summary: python tracing
Author-email: Your Name <your@email.com>
License: MIT License
License-File: LICENSE
Requires-Dist: m4rkw-pushover
Requires-Dist: requests
Requires-Dist: requests[socks]
Requires-Dist: PySocks
Requires-Dist: PyYAML
Dynamic: license-file
